setup.py
sqlalchemy_elasticquery/__init__.py
sqlalchemy_elasticquery/elastic_query.py
sqlalchemy_elasticquery.egg-info/PKG-INFO
sqlalchemy_elasticquery.egg-info/SOURCES.txt
sqlalchemy_elasticquery.egg-info/dependency_links.txt
sqlalchemy_elasticquery.egg-info/requires.txt
sqlalchemy_elasticquery.egg-info/top_level.txt
test/test.py