Metadata-Version: 1.1
Name: sqlalchemy-elasticquery
Version: 0.0.1
Summary: Use ElasticSearch query search in SQLAlchemy.
Home-page: https://github.com/loverajoel/sqlalchemy-elasticquery
Author: Joel Lovera
Author-email: joelalover@gmail.com
License: MIT
Platform: UNKNOWN
Classifier: Development Status :: 4 - Beta
Classifier: Environment :: Plugins
Classifier: License :: OSI Approved :: MIT License
Classifier: Operating System :: OS Independent
Classifier: Programming Language :: Python
Classifier: Topic :: Database
